wrapperWSD/__init__.py
wrapperWSD/wrapperWSD.py
wrapperWSD/resources/sensenindex2wd.pkl
wrapperWSD/resources/wd2wiki.pkl
wrapperWSD-0.0.4.dist-info/METADATA
wrapperWSD-0.0.4.dist-info/WHEEL
wrapperWSD-0.0.4.dist-info/top_level.txt
wrapperWSD-0.0.4.dist-info/RECORD
